{
  "_meta": {
    "last_updated": "2026-04-02T18:40:36.306402+00:00",
    "note": "Auto-updated by scraper/scraper.py \u2014 do not edit manually"
  },
  "stock": [
    {
      "release_id": 1,
      "retailers": [
        {
          "name": "Zatu",
          "status": "unknown",
          "url": "https://www.board-game.co.uk/search/?q=Mega%20Evolution%20%E2%80%94%20Ascended%20Heroes",
          "last_checked": "2026-04-02T18:40:36.306071+00:00"
        },
        {
          "name": "365 Games",
          "status": "unknown",
          "url": "https://www.365games.co.uk/search?q=Mega%20Evolution%20%E2%80%94%20Ascended%20Heroes",
          "last_checked": "2026-04-02T18:40:36.306103+00:00"
        },
        {
          "name": "Smyths",
          "status": "unknown",
          "url": "https://www.smythstoys.com/uk/en-gb/search/?text=Mega%20Evolution%20%E2%80%94%20Ascended%20Heroes",
          "last_checked": "2026-04-02T18:40:36.306110+00:00"
        }
      ]
    },
    {
      "release_id": 2,
      "retailers": [
        {
          "name": "Zatu",
          "status": "unknown",
          "url": "https://www.board-game.co.uk/search/?q=Mega%20Evolution%20%E2%80%94%20Perfect%20Order",
          "last_checked": "2026-04-02T18:40:36.306120+00:00"
        },
        {
          "name": "365 Games",
          "status": "unknown",
          "url": "https://www.365games.co.uk/search?q=Mega%20Evolution%20%E2%80%94%20Perfect%20Order",
          "last_checked": "2026-04-02T18:40:36.306125+00:00"
        },
        {
          "name": "Smyths",
          "status": "unknown",
          "url": "https://www.smythstoys.com/uk/en-gb/search/?text=Mega%20Evolution%20%E2%80%94%20Perfect%20Order",
          "last_checked": "2026-04-02T18:40:36.306129+00:00"
        }
      ]
    },
    {
      "release_id": 3,
      "retailers": [
        {
          "name": "Zatu",
          "status": "unknown",
          "url": "https://www.board-game.co.uk/search/?q=2025%20World%20Championships%20Decks",
          "last_checked": "2026-04-02T18:40:36.306138+00:00"
        },
        {
          "name": "365 Games",
          "status": "unknown",
          "url": "https://www.365games.co.uk/search?q=2025%20World%20Championships%20Decks",
          "last_checked": "2026-04-02T18:40:36.306145+00:00"
        },
        {
          "name": "Smyths",
          "status": "unknown",
          "url": "https://www.smythstoys.com/uk/en-gb/search/?text=2025%20World%20Championships%20Decks",
          "last_checked": "2026-04-02T18:40:36.306150+00:00"
        }
      ]
    },
    {
      "release_id": 4,
      "retailers": [
        {
          "name": "Zatu",
          "status": "unknown",
          "url": "https://www.board-game.co.uk/search/?q=Mega%20Evolution%20%E2%80%94%20Ascended%20Heroes%20Booster%20Bundle",
          "last_checked": "2026-04-02T18:40:36.306157+00:00"
        },
        {
          "name": "365 Games",
          "status": "unknown",
          "url": "https://www.365games.co.uk/search?q=Mega%20Evolution%20%E2%80%94%20Ascended%20Heroes%20Booster%20Bundle",
          "last_checked": "2026-04-02T18:40:36.306162+00:00"
        },
        {
          "name": "Smyths",
          "status": "unknown",
          "url": "https://www.smythstoys.com/uk/en-gb/search/?text=Mega%20Evolution%20%E2%80%94%20Ascended%20Heroes%20Booster%20Bundle",
          "last_checked": "2026-04-02T18:40:36.306166+00:00"
        }
      ]
    },
    {
      "release_id": 5,
      "retailers": [
        {
          "name": "Zatu",
          "status": "unknown",
          "url": "https://www.board-game.co.uk/search/?q=Mega%20Evolution%20%E2%80%94%20Chaos%20Rising",
          "last_checked": "2026-04-02T18:40:36.306173+00:00"
        },
        {
          "name": "365 Games",
          "status": "unknown",
          "url": "https://www.365games.co.uk/search?q=Mega%20Evolution%20%E2%80%94%20Chaos%20Rising",
          "last_checked": "2026-04-02T18:40:36.306177+00:00"
        },
        {
          "name": "Smyths",
          "status": "unknown",
          "url": "https://www.smythstoys.com/uk/en-gb/search/?text=Mega%20Evolution%20%E2%80%94%20Chaos%20Rising",
          "last_checked": "2026-04-02T18:40:36.306181+00:00"
        }
      ]
    },
    {
      "release_id": 6,
      "retailers": [
        {
          "name": "Zatu",
          "status": "unknown",
          "url": "https://www.board-game.co.uk/search/?q=Abyss%20Eye",
          "last_checked": "2026-04-02T18:40:36.306187+00:00"
        },
        {
          "name": "365 Games",
          "status": "unknown",
          "url": "https://www.365games.co.uk/search?q=Abyss%20Eye",
          "last_checked": "2026-04-02T18:40:36.306192+00:00"
        },
        {
          "name": "Smyths",
          "status": "unknown",
          "url": "https://www.smythstoys.com/uk/en-gb/search/?text=Abyss%20Eye",
          "last_checked": "2026-04-02T18:40:36.306196+00:00"
        }
      ]
    },
    {
      "release_id": 7,
      "retailers": [
        {
          "name": "Zatu",
          "status": "unknown",
          "url": "https://www.board-game.co.uk/search/?q=Storm%20Emeralda",
          "last_checked": "2026-04-02T18:40:36.306202+00:00"
        },
        {
          "name": "365 Games",
          "status": "unknown",
          "url": "https://www.365games.co.uk/search?q=Storm%20Emeralda",
          "last_checked": "2026-04-02T18:40:36.306207+00:00"
        },
        {
          "name": "Smyths",
          "status": "unknown",
          "url": "https://www.smythstoys.com/uk/en-gb/search/?text=Storm%20Emeralda",
          "last_checked": "2026-04-02T18:40:36.306211+00:00"
        }
      ]
    }
  ]
}